[
  {
    "name": "mÉ›É²gÄŸ",
    "command": "tt",
    "query": "https://vt.tiktok.com/ZSU3W246x/",
    "time": "07:45:40",
    "number": "64820200128618",
    "group": "Medusa Group Chat | Bot : Online 24 jam"
  },
  {
    "name": ".~",
    "command": "tt",
    "query": "https://vt.tiktok.com/ZSU37Bfka/",
    "time": "07:54:01",
    "number": "154610702541020",
    "group": "Medusa Group Chat | Bot : Online 24 jam"
  },
  {
    "name": "ğ“±ğ“¾ğ“ªğ“·ğ“°.",
    "command": "tt",
    "query": "https://vm.tiktok.com/ZSHv4674XYNtA-afbwB/",
    "time": "08:17:53",
    "number": "279693152510126",
    "group": "Medusa Group Chat | Bot : Online 24 jam"
  }
]